{
  "id": 3014054307,
  "id_str": "3014054307",
  "name": "Разработчик",
  "screen_name": "jsunderhood",
  "location": "Chernihiv",
  "profile_location": null,
  "description": "Shared Twitter account for Russian-speaking frontend developers with a new author every week. Currently led by @roman01la",
  "url": "https://t.co/siMww4DDBv",
  "entities": {
    "url": {
      "urls": [
        {
          "url": "https://t.co/siMww4DDBv",
          "expanded_url": "https://jsunderhood.ru/",
          "display_url": "jsunderhood.ru",
          "indices": [
            0,
            23
          ]
        }
      ]
    },
    "description": {
      "urls": []
    }
  },
  "protected": false,
  "followers_count": 3150,
  "friends_count": 68,
  "listed_count": 179,
  "created_at": "Tue Feb 03 07:35:41 +0000 2015",
  "favourites_count": 149,
  "utc_offset": 3600,
  "time_zone": "London",
  "geo_enabled": true,
  "verified": false,
  "statuses_count": 19487,
  "lang": "ru",
  "status": {
    "created_at": "Sat Apr 16 17:13:29 +0000 2016",
    "id": 721386040183943200,
    "id_str": "721386040183943168",
    "text": "Думаю уже получилось. Если я правильно понял, то все это уже работает на устройствах пользователей. https://t.co/6dYBXmpg71",
    "entities": {
      "hashtags": [],
      "symbols": [],
      "user_mentions": [],
      "urls": [
        {
          "url": "https://t.co/6dYBXmpg71",
          "expanded_url": "https://twitter.com/trufid/status/721385373155377153",
          "display_url": "twitter.com/trufid/status/…",
          "indices": [
            100,
            123
          ]
        }
      ]
    },
    "truncated": false,
    "source": "<a href=\"http://twitter.com/download/iphone\" rel=\"nofollow\">Twitter for iPhone</a>",
    "in_reply_to_status_id": null,
    "in_reply_to_status_id_str": null,
    "in_reply_to_user_id": null,
    "in_reply_to_user_id_str": null,
    "in_reply_to_screen_name": null,
    "geo": null,
    "coordinates": null,
    "place": null,
    "contributors": null,
    "quoted_status_id": 721385373155377200,
    "quoted_status_id_str": "721385373155377153",
    "is_quote_status": true,
    "retweet_count": 0,
    "favorite_count": 0,
    "favorited": false,
    "retweeted": false,
    "possibly_sensitive": false,
    "lang": "ru"
  },
  "contributors_enabled": false,
  "is_translator": false,
  "is_translation_enabled": false,
  "profile_background_color": "FAFAFA",
  "profile_background_image_url": "http://abs.twimg.com/images/themes/theme1/bg.png",
  "profile_background_image_url_https": "https://abs.twimg.com/images/themes/theme1/bg.png",
  "profile_background_tile": false,
  "profile_image_url": "http://pbs.twimg.com/profile_images/719468824588779520/HE4ubjRs_normal.jpg",
  "profile_image_url_https": "https://pbs.twimg.com/profile_images/719468824588779520/HE4ubjRs_normal.jpg",
  "profile_banner_url": "https://pbs.twimg.com/profile_banners/3014054307/1460369818",
  "profile_link_color": "0084B4",
  "profile_sidebar_border_color": "C0DEED",
  "profile_sidebar_fill_color": "DDEEF6",
  "profile_text_color": "333333",
  "profile_use_background_image": false,
  "has_extended_profile": false,
  "default_profile": false,
  "default_profile_image": false,
  "following": false,
  "follow_request_sent": false,
  "notifications": false,
  "suspended": false,
  "needs_phone_verification": false
}
