{
  "mentions": [
    {
      "created_at": "Mon May 30 09:03:04 +0000 2016",
      "id": 737207689525252100,
      "id_str": "737207689525252096",
      "text": "@jsunderhood @twilightfeel ох ее )\nчую будет мясо :)",
      "truncated": false,
      "entities": {
        "hashtags": [],
        "symbols": [],
        "user_mentions": [
          {
            "screen_name": "jsunderhood",
            "name": "Разработчик",
            "id": 3014054307,
            "id_str": "3014054307",
            "indices": [
              0,
              12
            ]
          },
          {
            "screen_name": "twilightfeel",
            "name": "Phillip Kovalev",
            "id": 122621043,
            "id_str": "122621043",
            "indices": [
              13,
              26
            ]
          }
        ],
        "urls": []
      },
      "source": "<a href=\"http://tapbots.com/software/tweetbot/mac\" rel=\"nofollow\">Tweetbot for Mac</a>",
      "in_reply_to_status_id": 737207329624588300,
      "in_reply_to_status_id_str": "737207329624588289",
      "in_reply_to_user_id": 3014054307,
      "in_reply_to_user_id_str": "3014054307",
      "in_reply_to_screen_name": "jsunderhood",
      "user": {
        "id": 185156694,
        "id_str": "185156694"
      },
      "geo": null,
      "coordinates": null,
      "place": null,
      "contributors": null,
      "is_quote_status": false,
      "retweet_count": 0,
      "favorite_count": 0,
      "favorited": false,
      "retweeted": false,
      "lang": "ru"
    },
    {
      "created_at": "Mon May 30 09:05:25 +0000 2016",
      "id": 737208279730901000,
      "id_str": "737208279730900992",
      "text": "Эту неделю @twilightfeel ведёт @jsunderhood. Срочно подписывайтесь, ваш любимый джаваскрипт еще так не унижали!",
      "truncated": false,
      "entities": {
        "hashtags": [],
        "symbols": [],
        "user_mentions": [
          {
            "screen_name": "twilightfeel",
            "name": "Phillip Kovalev",
            "id": 122621043,
            "id_str": "122621043",
            "indices": [
              11,
              24
            ]
          },
          {
            "screen_name": "jsunderhood",
            "name": "Разработчик",
            "id": 3014054307,
            "id_str": "3014054307",
            "indices": [
              31,
              43
            ]
          }
        ],
        "urls": []
      },
      "source": "<a href=\"http://twitter.com\" rel=\"nofollow\">Twitter Web Client</a>",
      "in_reply_to_status_id": null,
      "in_reply_to_status_id_str": null,
      "in_reply_to_user_id": null,
      "in_reply_to_user_id_str": null,
      "in_reply_to_screen_name": null,
      "user": {
        "id": 160556349,
        "id_str": "160556349"
      },
      "geo": null,
      "coordinates": null,
      "place": null,
      "contributors": null,
      "is_quote_status": false,
      "retweet_count": 1,
      "favorite_count": 0,
      "favorited": false,
      "retweeted": false,
      "lang": "ru"
    }
  ]
}
